MANIFEST.in
README.md
dev.requirements.txt
requirements.txt
setup.py
tgcli/__init__.py
tgcli.egg-info/PKG-INFO
tgcli.egg-info/SOURCES.txt
tgcli.egg-info/dependency_links.txt
tgcli.egg-info/entry_points.txt
tgcli.egg-info/not-zip-safe
tgcli.egg-info/requires.txt
tgcli.egg-info/top_level.txt
tgcli/cli/__init__.py
tgcli/cli/bot/__init__.py
tgcli/cli/bot/send.py
tgcli/request/__init__.py
tgcli/request/bot.py