Metadata-Version: 2.1
Name: tgcli
Version: 0.3.1
Summary: tgcli is a client tool for Telegram.
Home-page: https://github.com/erayerdin/tgcli
Author: Eray Erdin
Author-email: eraygezer.94@gmail.com
License: Apache License 2.0
Download-URL: https://github.com/erayerdin/tgcli/archive/v0.3.1.tar.gz
Keywords: telegram messaging communication terminal tool cli
Platform: UNKNOWN
Classifier: Development Status :: 5 - Production/Stable
Classifier: Intended Audience :: Developers
Classifier: Intended Audience :: System Administrators
Classifier: License :: OSI Approved :: Apache Software License
Classifier: Programming Language :: Python :: 3 :: Only
Classifier: Programming Language :: Python :: 3.5
Classifier: Programming Language :: Python :: 3.6
Classifier: Programming Language :: Python :: 3.7
Classifier: Topic :: Communications :: Chat
